fundNSF/__init__.py
fundNSF/fundNSF.py
fundNSF/fundNSF_test.py
fundNSF-0.0.334.dist-info/LICENSE
fundNSF-0.0.334.dist-info/METADATA
fundNSF-0.0.334.dist-info/WHEEL
fundNSF-0.0.334.dist-info/top_level.txt
fundNSF-0.0.334.dist-info/RECORD
