Metadata-Version: 2.1
Name: fundNSF
Version: 0.0.334
Summary: Searches National Science Foundation awards database
Home-page: https://github.com/C-NoBlok/fundNSF
Author: Jacob Noble
Author-email: jacob.a.noble@gmail.com
License: UNKNOWN
Keywords: api,National Science Foundation,NSF
Platform: UNKNOWN
Classifier: Programming Language :: Python :: 3
Classifier: License :: OSI Approved :: MIT License
Classifier: Operating System :: OS Independent
Requires-Dist: requests (==2.20.0)
